[
  {
    "languages": [
      {
        "name": "TypeScript",
        "total_seconds": 15450.987166,
        "digital": "4:17:30",
        "decimal": "4.28",
        "text": "4 hrs 17 mins",
        "hours": 4,
        "minutes": 17,
        "seconds": 30,
        "percent": 99.9
      },
      {
        "name": "Other",
        "total_seconds": 14.769656,
        "digital": "0:00:14",
        "decimal": "0.00",
        "text": "14 secs",
        "hours": 0,
        "minutes": 0,
        "seconds": 14,
        "percent": 0.1
      },
      {
        "name": "TSConfig",
        "total_seconds": 1.145401,
        "digital": "0:00:01",
        "decimal": "0.00",
        "text": "1 sec",
        "hours": 0,
        "minutes": 0,
        "seconds": 1,
        "percent": 0.01
      }
    ],
    "grand_total": {
      "hours": 4,
      "minutes": 17,
      "total_seconds": 15466.902223,
      "digital": "4:17",
      "decimal": "4.28",
      "text": "4 hrs 17 mins"
    },
    "editors": [
      {
        "name": "VS Code",
        "total_seconds": 15466.902223,
        "digital": "4:17:46",
        "decimal": "4.28",
        "text": "4 hrs 17 mins",
        "hours": 4,
        "minutes": 17,
        "seconds": 46,
        "percent": 100
      }
    ],
    "operating_systems": [
      {
        "name": "Mac",
        "total_seconds": 15466.902223,
        "digital": "4:17:46",
        "decimal": "4.28",
        "text": "4 hrs 17 mins",
        "hours": 4,
        "minutes": 17,
        "seconds": 46,
        "percent": 100
      }
    ],
    "categories": [
      {
        "name": "Coding",
        "total_seconds": 15466.902223,
        "digital": "4:17:46",
        "decimal": "4.28",
        "text": "4 hrs 17 mins",
        "hours": 4,
        "minutes": 17,
        "seconds": 46,
        "percent": 100
      }
    ],
    "dependencies": [
      {
        "name": "stripe",
        "total_seconds": 12109.166699,
        "digital": "3:21:49",
        "decimal": "3.35",
        "text": "3 hrs 21 mins",
        "hours": 3,
        "minutes": 21,
        "seconds": 49,
        "percent": 7.85
      },
      {
        "name": "icons-react",
        "total_seconds": 10802.181412,
        "digital": "3:00:02",
        "decimal": "3.00",
        "text": "3 hrs",
        "hours": 3,
        "minutes": 0,
        "seconds": 2,
        "percent": 7.01
      },
      {
        "name": "fetch",
        "total_seconds": 10799.056649,
        "digital": "2:59:59",
        "decimal": "2.98",
        "text": "2 hrs 59 mins",
        "hours": 2,
        "minutes": 59,
        "seconds": 59,
        "percent": 7
      },
      {
        "name": "utils",
        "total_seconds": 10739.099073,
        "digital": "2:58:59",
        "decimal": "2.97",
        "text": "2 hrs 58 mins",
        "hours": 2,
        "minutes": 58,
        "seconds": 59,
        "percent": 6.97
      },
      {
        "name": "react",
        "total_seconds": 9425.443888,
        "digital": "2:37:05",
        "decimal": "2.62",
        "text": "2 hrs 37 mins",
        "hours": 2,
        "minutes": 37,
        "seconds": 5,
        "percent": 6.11
      },
      {
        "name": "client",
        "total_seconds": 6920.924779,
        "digital": "1:55:20",
        "decimal": "1.92",
        "text": "1 hr 55 mins",
        "hours": 1,
        "minutes": 55,
        "seconds": 20,
        "percent": 4.49
      },
      {
        "name": "react-query",
        "total_seconds": 6772.179539,
        "digital": "1:52:52",
        "decimal": "1.87",
        "text": "1 hr 52 mins",
        "hours": 1,
        "minutes": 52,
        "seconds": 52,
        "percent": 4.39
      },
      {
        "name": "async-button",
        "total_seconds": 6708.593774,
        "digital": "1:51:48",
        "decimal": "1.85",
        "text": "1 hr 51 mins",
        "hours": 1,
        "minutes": 51,
        "seconds": 48,
        "percent": 4.35
      },
      {
        "name": "spinner",
        "total_seconds": 6702.582902,
        "digital": "1:51:42",
        "decimal": "1.85",
        "text": "1 hr 51 mins",
        "hours": 1,
        "minutes": 51,
        "seconds": 42,
        "percent": 4.35
      },
      {
        "name": "view-errors",
        "total_seconds": 6700.12486,
        "digital": "1:51:40",
        "decimal": "1.85",
        "text": "1 hr 51 mins",
        "hours": 1,
        "minutes": 51,
        "seconds": 40,
        "percent": 4.35
      },
      {
        "name": "progress",
        "total_seconds": 6659.826488,
        "digital": "1:50:59",
        "decimal": "1.83",
        "text": "1 hr 50 mins",
        "hours": 1,
        "minutes": 50,
        "seconds": 59,
        "percent": 4.32
      },
      {
        "name": "button",
        "total_seconds": 6236.903898,
        "digital": "1:43:56",
        "decimal": "1.72",
        "text": "1 hr 43 mins",
        "hours": 1,
        "minutes": 43,
        "seconds": 56,
        "percent": 4.05
      },
      {
        "name": "comparison",
        "total_seconds": 6155.392141,
        "digital": "1:42:35",
        "decimal": "1.70",
        "text": "1 hr 42 mins",
        "hours": 1,
        "minutes": 42,
        "seconds": 35,
        "percent": 3.99
      },
      {
        "name": "confirm-dialog",
        "total_seconds": 5253.637028,
        "digital": "1:27:33",
        "decimal": "1.45",
        "text": "1 hr 27 mins",
        "hours": 1,
        "minutes": 27,
        "seconds": 33,
        "percent": 3.41
      },
      {
        "name": "global-actions-context",
        "total_seconds": 4819.17822,
        "digital": "1:20:19",
        "decimal": "1.33",
        "text": "1 hr 20 mins",
        "hours": 1,
        "minutes": 20,
        "seconds": 19,
        "percent": 3.13
      },
      {
        "name": "query",
        "total_seconds": 4459.619119,
        "digital": "1:14:19",
        "decimal": "1.23",
        "text": "1 hr 14 mins",
        "hours": 1,
        "minutes": 14,
        "seconds": 19,
        "percent": 2.89
      },
      {
        "name": "use-toast",
        "total_seconds": 4441.729797,
        "digital": "1:14:01",
        "decimal": "1.23",
        "text": "1 hr 14 mins",
        "hours": 1,
        "minutes": 14,
        "seconds": 1,
        "percent": 2.88
      },
      {
        "name": "react-slider",
        "total_seconds": 4066.816525,
        "digital": "1:07:46",
        "decimal": "1.12",
        "text": "1 hr 7 mins",
        "hours": 1,
        "minutes": 7,
        "seconds": 46,
        "percent": 2.64
      },
      {
        "name": "cta",
        "total_seconds": 4066.816525,
        "digital": "1:07:46",
        "decimal": "1.12",
        "text": "1 hr 7 mins",
        "hours": 1,
        "minutes": 7,
        "seconds": 46,
        "percent": 2.64
      },
      {
        "name": "question-tooltip",
        "total_seconds": 4035.054622,
        "digital": "1:07:15",
        "decimal": "1.12",
        "text": "1 hr 7 mins",
        "hours": 1,
        "minutes": 7,
        "seconds": 15,
        "percent": 2.62
      },
      {
        "name": "billing",
        "total_seconds": 3710.589257,
        "digital": "1:01:50",
        "decimal": "1.02",
        "text": "1 hr 1 min",
        "hours": 1,
        "minutes": 1,
        "seconds": 50,
        "percent": 2.41
      },
      {
        "name": "zod",
        "total_seconds": 1746.138643,
        "digital": "0:29:06",
        "decimal": "0.48",
        "text": "29 mins",
        "hours": 0,
        "minutes": 29,
        "seconds": 6,
        "percent": 1.13
      },
      {
        "name": "hono",
        "total_seconds": 1631.54888,
        "digital": "0:27:11",
        "decimal": "0.45",
        "text": "27 mins",
        "hours": 0,
        "minutes": 27,
        "seconds": 11,
        "percent": 1.06
      },
      {
        "name": "http-exception",
        "total_seconds": 1063.674564,
        "digital": "0:17:43",
        "decimal": "0.28",
        "text": "17 mins",
        "hours": 0,
        "minutes": 17,
        "seconds": 43,
        "percent": 0.69
      },
      {
        "name": "teams-$teamId-helpers",
        "total_seconds": 1055.851983,
        "digital": "0:17:35",
        "decimal": "0.28",
        "text": "17 mins",
        "hours": 0,
        "minutes": 17,
        "seconds": 35,
        "percent": 0.68
      },
      {
        "name": "prisma",
        "total_seconds": 1055.851983,
        "digital": "0:17:35",
        "decimal": "0.28",
        "text": "17 mins",
        "hours": 0,
        "minutes": 17,
        "seconds": 35,
        "percent": 0.68
      },
      {
        "name": "auth-helpers",
        "total_seconds": 1055.851983,
        "digital": "0:17:35",
        "decimal": "0.28",
        "text": "17 mins",
        "hours": 0,
        "minutes": 17,
        "seconds": 35,
        "percent": 0.68
      },
      {
        "name": "id",
        "total_seconds": 1055.851983,
        "digital": "0:17:35",
        "decimal": "0.28",
        "text": "17 mins",
        "hours": 0,
        "minutes": 17,
        "seconds": 35,
        "percent": 0.68
      },
      {
        "name": "post-auth-checkout",
        "total_seconds": 765.502918,
        "digital": "0:12:45",
        "decimal": "0.20",
        "text": "12 mins",
        "hours": 0,
        "minutes": 12,
        "seconds": 45,
        "percent": 0.5
      },
      {
        "name": "logger",
        "total_seconds": 442.221514,
        "digital": "0:07:22",
        "decimal": "0.12",
        "text": "7 mins",
        "hours": 0,
        "minutes": 7,
        "seconds": 22,
        "percent": 0.29
      },
      {
        "name": "axios",
        "total_seconds": 241.747421,
        "digital": "0:04:01",
        "decimal": "0.07",
        "text": "4 mins",
        "hours": 0,
        "minutes": 4,
        "seconds": 1,
        "percent": 0.16
      },
      {
        "name": "testimonial",
        "total_seconds": 241.305646,
        "digital": "0:04:01",
        "decimal": "0.07",
        "text": "4 mins",
        "hours": 0,
        "minutes": 4,
        "seconds": 1,
        "percent": 0.16
      },
      {
        "name": "logos",
        "total_seconds": 241.305646,
        "digital": "0:04:01",
        "decimal": "0.07",
        "text": "4 mins",
        "hours": 0,
        "minutes": 4,
        "seconds": 1,
        "percent": 0.16
      },
      {
        "name": "p-retry",
        "total_seconds": 236.701652,
        "digital": "0:03:56",
        "decimal": "0.05",
        "text": "3 mins",
        "hours": 0,
        "minutes": 3,
        "seconds": 56,
        "percent": 0.15
      },
      {
        "name": "slack",
        "total_seconds": 228.879071,
        "digital": "0:03:48",
        "decimal": "0.05",
        "text": "3 mins",
        "hours": 0,
        "minutes": 3,
        "seconds": 48,
        "percent": 0.15
      },
      {
        "name": "dialog",
        "total_seconds": 166.308756,
        "digital": "0:02:46",
        "decimal": "0.03",
        "text": "2 mins",
        "hours": 0,
        "minutes": 2,
        "seconds": 46,
        "percent": 0.11
      },
      {
        "name": "view-container",
        "total_seconds": 49.304024,
        "digital": "0:00:49",
        "decimal": "0.00",
        "text": "49 secs",
        "hours": 0,
        "minutes": 0,
        "seconds": 49,
        "percent": 0.03
      },
      {
        "name": "loadable-button",
        "total_seconds": 47.671686,
        "digital": "0:00:47",
        "decimal": "0.00",
        "text": "47 secs",
        "hours": 0,
        "minutes": 0,
        "seconds": 47,
        "percent": 0.03
      },
      {
        "name": "input",
        "total_seconds": 43.332776,
        "digital": "0:00:43",
        "decimal": "0.00",
        "text": "43 secs",
        "hours": 0,
        "minutes": 0,
        "seconds": 43,
        "percent": 0.03
      },
      {
        "name": "form",
        "total_seconds": 41.926984,
        "digital": "0:00:41",
        "decimal": "0.00",
        "text": "41 secs",
        "hours": 0,
        "minutes": 0,
        "seconds": 41,
        "percent": 0.03
      },
      {
        "name": "react-hook-form",
        "total_seconds": 41.926984,
        "digital": "0:00:41",
        "decimal": "0.00",
        "text": "41 secs",
        "hours": 0,
        "minutes": 0,
        "seconds": 41,
        "percent": 0.03
      },
      {
        "name": "checkbox",
        "total_seconds": 40.60476,
        "digital": "0:00:40",
        "decimal": "0.00",
        "text": "40 secs",
        "hours": 0,
        "minutes": 0,
        "seconds": 40,
        "percent": 0.03
      },
      {
        "name": "view-modal",
        "total_seconds": 34.55367,
        "digital": "0:00:34",
        "decimal": "0.00",
        "text": "34 secs",
        "hours": 0,
        "minutes": 0,
        "seconds": 34,
        "percent": 0.02
      },
      {
        "name": "use-user",
        "total_seconds": 33.528193,
        "digital": "0:00:33",
        "decimal": "0.00",
        "text": "33 secs",
        "hours": 0,
        "minutes": 0,
        "seconds": 33,
        "percent": 0.02
      },
      {
        "name": "preferences-store",
        "total_seconds": 32.913424,
        "digital": "0:00:32",
        "decimal": "0.00",
        "text": "32 secs",
        "hours": 0,
        "minutes": 0,
        "seconds": 32,
        "percent": 0.02
      },
      {
        "name": "next",
        "total_seconds": 32.704429,
        "digital": "0:00:32",
        "decimal": "0.00",
        "text": "32 secs",
        "hours": 0,
        "minutes": 0,
        "seconds": 32,
        "percent": 0.02
      },
      {
        "name": "header",
        "total_seconds": 32.704429,
        "digital": "0:00:32",
        "decimal": "0.00",
        "text": "32 secs",
        "hours": 0,
        "minutes": 0,
        "seconds": 32,
        "percent": 0.02
      },
      {
        "name": "js-cookie",
        "total_seconds": 32.625258,
        "digital": "0:00:32",
        "decimal": "0.00",
        "text": "32 secs",
        "hours": 0,
        "minutes": 0,
        "seconds": 32,
        "percent": 0.02
      },
      {
        "name": "use-team",
        "total_seconds": 30.781135,
        "digital": "0:00:30",
        "decimal": "0.00",
        "text": "30 secs",
        "hours": 0,
        "minutes": 0,
        "seconds": 30,
        "percent": 0.02
      },
      {
        "name": "use-infinite-list",
        "total_seconds": 26.902552,
        "digital": "0:00:26",
        "decimal": "0.00",
        "text": "26 secs",
        "hours": 0,
        "minutes": 0,
        "seconds": 26,
        "percent": 0.02
      },
      {
        "name": "billing-message",
        "total_seconds": 26.505928,
        "digital": "0:00:26",
        "decimal": "0.00",
        "text": "26 secs",
        "hours": 0,
        "minutes": 0,
        "seconds": 26,
        "percent": 0.02
      },
      {
        "name": "local",
        "total_seconds": 22.929341,
        "digital": "0:00:22",
        "decimal": "0.00",
        "text": "22 secs",
        "hours": 0,
        "minutes": 0,
        "seconds": 22,
        "percent": 0.01
      },
      {
        "name": "posthog-js",
        "total_seconds": 22.929341,
        "digital": "0:00:22",
        "decimal": "0.00",
        "text": "22 secs",
        "hours": 0,
        "minutes": 0,
        "seconds": 22,
        "percent": 0.01
      },
      {
        "name": "find-resource-modal",
        "total_seconds": 15.10676,
        "digital": "0:00:15",
        "decimal": "0.00",
        "text": "15 secs",
        "hours": 0,
        "minutes": 0,
        "seconds": 15,
        "percent": 0.01
      },
      {
        "name": "use-user-identify",
        "total_seconds": 15.10676,
        "digital": "0:00:15",
        "decimal": "0.00",
        "text": "15 secs",
        "hours": 0,
        "minutes": 0,
        "seconds": 15,
        "percent": 0.01
      },
      {
        "name": "command-bar",
        "total_seconds": 15.10676,
        "digital": "0:00:15",
        "decimal": "0.00",
        "text": "15 secs",
        "hours": 0,
        "minutes": 0,
        "seconds": 15,
        "percent": 0.01
      },
      {
        "name": "navigation",
        "total_seconds": 15.10676,
        "digital": "0:00:15",
        "decimal": "0.00",
        "text": "15 secs",
        "hours": 0,
        "minutes": 0,
        "seconds": 15,
        "percent": 0.01
      },
      {
        "name": "feedback-modal",
        "total_seconds": 15.10676,
        "digital": "0:00:15",
        "decimal": "0.00",
        "text": "15 secs",
        "hours": 0,
        "minutes": 0,
        "seconds": 15,
        "percent": 0.01
      },
      {
        "name": "use-theme-class",
        "total_seconds": 15.10676,
        "digital": "0:00:15",
        "decimal": "0.00",
        "text": "15 secs",
        "hours": 0,
        "minutes": 0,
        "seconds": 15,
        "percent": 0.01
      },
      {
        "name": "react-headless",
        "total_seconds": 15.10676,
        "digital": "0:00:15",
        "decimal": "0.00",
        "text": "15 secs",
        "hours": 0,
        "minutes": 0,
        "seconds": 15,
        "percent": 0.01
      },
      {
        "name": "analytics-next",
        "total_seconds": 15.10676,
        "digital": "0:00:15",
        "decimal": "0.00",
        "text": "15 secs",
        "hours": 0,
        "minutes": 0,
        "seconds": 15,
        "percent": 0.01
      },
      {
        "name": "link",
        "total_seconds": 14.352151,
        "digital": "0:00:14",
        "decimal": "0.00",
        "text": "14 secs",
        "hours": 0,
        "minutes": 0,
        "seconds": 14,
        "percent": 0.01
      },
      {
        "name": "apollo-helpers",
        "total_seconds": 12.86835,
        "digital": "0:00:12",
        "decimal": "0.00",
        "text": "12 secs",
        "hours": 0,
        "minutes": 0,
        "seconds": 12,
        "percent": 0.01
      },
      {
        "name": "env",
        "total_seconds": 12.86835,
        "digital": "0:00:12",
        "decimal": "0.00",
        "text": "12 secs",
        "hours": 0,
        "minutes": 0,
        "seconds": 12,
        "percent": 0.01
      },
      {
        "name": "teams-$teamId-lists-route",
        "total_seconds": 11.952183,
        "digital": "0:00:11",
        "decimal": "0.00",
        "text": "11 secs",
        "hours": 0,
        "minutes": 0,
        "seconds": 11,
        "percent": 0.01
      },
      {
        "name": "get-teams-$teamId-events",
        "total_seconds": 11.952183,
        "digital": "0:00:11",
        "decimal": "0.00",
        "text": "11 secs",
        "hours": 0,
        "minutes": 0,
        "seconds": 11,
        "percent": 0.01
      },
      {
        "name": "post-teams-$teamId-billing-portal",
        "total_seconds": 11.952183,
        "digital": "0:00:11",
        "decimal": "0.00",
        "text": "11 secs",
        "hours": 0,
        "minutes": 0,
        "seconds": 11,
        "percent": 0.01
      },
      {
        "name": "teams-$teamId-domains-route",
        "total_seconds": 11.952183,
        "digital": "0:00:11",
        "decimal": "0.00",
        "text": "11 secs",
        "hours": 0,
        "minutes": 0,
        "seconds": 11,
        "percent": 0.01
      },
      {
        "name": "teams-$teamId-memberships-route",
        "total_seconds": 11.952183,
        "digital": "0:00:11",
        "decimal": "0.00",
        "text": "11 secs",
        "hours": 0,
        "minutes": 0,
        "seconds": 11,
        "percent": 0.01
      },
      {
        "name": "get-teams-$teamId-webhooks-portal",
        "total_seconds": 11.952183,
        "digital": "0:00:11",
        "decimal": "0.00",
        "text": "11 secs",
        "hours": 0,
        "minutes": 0,
        "seconds": 11,
        "percent": 0.01
      },
      {
        "name": "teams-$teamId-connections-router",
        "total_seconds": 11.952183,
        "digital": "0:00:11",
        "decimal": "0.00",
        "text": "11 secs",
        "hours": 0,
        "minutes": 0,
        "seconds": 11,
        "percent": 0.01
      },
      {
        "name": "teams-$teamId-mailboxes-route",
        "total_seconds": 11.952183,
        "digital": "0:00:11",
        "decimal": "0.00",
        "text": "11 secs",
        "hours": 0,
        "minutes": 0,
        "seconds": 11,
        "percent": 0.01
      },
      {
        "name": "teams-$teamId-feature-flags-route",
        "total_seconds": 11.952183,
        "digital": "0:00:11",
        "decimal": "0.00",
        "text": "11 secs",
        "hours": 0,
        "minutes": 0,
        "seconds": 11,
        "percent": 0.01
      },
      {
        "name": "get-teams-$teamId-credit-usage",
        "total_seconds": 11.952183,
        "digital": "0:00:11",
        "decimal": "0.00",
        "text": "11 secs",
        "hours": 0,
        "minutes": 0,
        "seconds": 11,
        "percent": 0.01
      },
      {
        "name": "get-teams-$teamId-billing",
        "total_seconds": 11.952183,
        "digital": "0:00:11",
        "decimal": "0.00",
        "text": "11 secs",
        "hours": 0,
        "minutes": 0,
        "seconds": 11,
        "percent": 0.01
      },
      {
        "name": "get-teams-$teamId",
        "total_seconds": 11.952183,
        "digital": "0:00:11",
        "decimal": "0.00",
        "text": "11 secs",
        "hours": 0,
        "minutes": 0,
        "seconds": 11,
        "percent": 0.01
      },
      {
        "name": "patch-teams-$teamId-outbound-settings",
        "total_seconds": 11.952183,
        "digital": "0:00:11",
        "decimal": "0.00",
        "text": "11 secs",
        "hours": 0,
        "minutes": 0,
        "seconds": 11,
        "percent": 0.01
      },
      {
        "name": "teams-$teamId-companies-router",
        "total_seconds": 11.952183,
        "digital": "0:00:11",
        "decimal": "0.00",
        "text": "11 secs",
        "hours": 0,
        "minutes": 0,
        "seconds": 11,
        "percent": 0.01
      },
      {
        "name": "get-teams-$teamId-outbound-settings",
        "total_seconds": 11.952183,
        "digital": "0:00:11",
        "decimal": "0.00",
        "text": "11 secs",
        "hours": 0,
        "minutes": 0,
        "seconds": 11,
        "percent": 0.01
      },
      {
        "name": "editor-route",
        "total_seconds": 11.952183,
        "digital": "0:00:11",
        "decimal": "0.00",
        "text": "11 secs",
        "hours": 0,
        "minutes": 0,
        "seconds": 11,
        "percent": 0.01
      },
      {
        "name": "teams-$teamId-analytics",
        "total_seconds": 11.952183,
        "digital": "0:00:11",
        "decimal": "0.00",
        "text": "11 secs",
        "hours": 0,
        "minutes": 0,
        "seconds": 11,
        "percent": 0.01
      },
      {
        "name": "delete-teams-$teamId",
        "total_seconds": 11.952183,
        "digital": "0:00:11",
        "decimal": "0.00",
        "text": "11 secs",
        "hours": 0,
        "minutes": 0,
        "seconds": 11,
        "percent": 0.01
      },
      {
        "name": "post-teams-$teamId-clear",
        "total_seconds": 11.952183,
        "digital": "0:00:11",
        "decimal": "0.00",
        "text": "11 secs",
        "hours": 0,
        "minutes": 0,
        "seconds": 11,
        "percent": 0.01
      },
      {
        "name": "teams-$teamId-actions-route",
        "total_seconds": 11.952183,
        "digital": "0:00:11",
        "decimal": "0.00",
        "text": "11 secs",
        "hours": 0,
        "minutes": 0,
        "seconds": 11,
        "percent": 0.01
      },
      {
        "name": "post-teams-$teamId-export",
        "total_seconds": 11.952183,
        "digital": "0:00:11",
        "decimal": "0.00",
        "text": "11 secs",
        "hours": 0,
        "minutes": 0,
        "seconds": 11,
        "percent": 0.01
      },
      {
        "name": "get-teams-$teamId-subscription-metadata",
        "total_seconds": 11.952183,
        "digital": "0:00:11",
        "decimal": "0.00",
        "text": "11 secs",
        "hours": 0,
        "minutes": 0,
        "seconds": 11,
        "percent": 0.01
      },
      {
        "name": "get-teams-$teamId-metadata",
        "total_seconds": 11.952183,
        "digital": "0:00:11",
        "decimal": "0.00",
        "text": "11 secs",
        "hours": 0,
        "minutes": 0,
        "seconds": 11,
        "percent": 0.01
      },
      {
        "name": "teams-$teamId-contacts-router",
        "total_seconds": 11.952183,
        "digital": "0:00:11",
        "decimal": "0.00",
        "text": "11 secs",
        "hours": 0,
        "minutes": 0,
        "seconds": 11,
        "percent": 0.01
      },
      {
        "name": "post-teams-$teamId-checkout",
        "total_seconds": 11.952183,
        "digital": "0:00:11",
        "decimal": "0.00",
        "text": "11 secs",
        "hours": 0,
        "minutes": 0,
        "seconds": 11,
        "percent": 0.01
      },
      {
        "name": "post-teams-$teamId-recalculate-health-score",
        "total_seconds": 11.952183,
        "digital": "0:00:11",
        "decimal": "0.00",
        "text": "11 secs",
        "hours": 0,
        "minutes": 0,
        "seconds": 11,
        "percent": 0.01
      },
      {
        "name": "get-teams-$teamId-credit-usage-count",
        "total_seconds": 11.952183,
        "digital": "0:00:11",
        "decimal": "0.00",
        "text": "11 secs",
        "hours": 0,
        "minutes": 0,
        "seconds": 11,
        "percent": 0.01
      },
      {
        "name": "teams-$teamId-api-keys-route",
        "total_seconds": 11.952183,
        "digital": "0:00:11",
        "decimal": "0.00",
        "text": "11 secs",
        "hours": 0,
        "minutes": 0,
        "seconds": 11,
        "percent": 0.01
      },
      {
        "name": "patch-teams-$teamId",
        "total_seconds": 11.952183,
        "digital": "0:00:11",
        "decimal": "0.00",
        "text": "11 secs",
        "hours": 0,
        "minutes": 0,
        "seconds": 11,
        "percent": 0.01
      },
      {
        "name": "get-teams-$teamId-events-count",
        "total_seconds": 11.952183,
        "digital": "0:00:11",
        "decimal": "0.00",
        "text": "11 secs",
        "hours": 0,
        "minutes": 0,
        "seconds": 11,
        "percent": 0.01
      },
      {
        "name": "patch-teams-$teamId-metadata",
        "total_seconds": 11.952183,
        "digital": "0:00:11",
        "decimal": "0.00",
        "text": "11 secs",
        "hours": 0,
        "minutes": 0,
        "seconds": 11,
        "percent": 0.01
      },
      {
        "name": "post-teams-$teamId-archive",
        "total_seconds": 11.952183,
        "digital": "0:00:11",
        "decimal": "0.00",
        "text": "11 secs",
        "hours": 0,
        "minutes": 0,
        "seconds": 11,
        "percent": 0.01
      },
      {
        "name": "teams-$teamId-campaigns-router",
        "total_seconds": 11.952183,
        "digital": "0:00:11",
        "decimal": "0.00",
        "text": "11 secs",
        "hours": 0,
        "minutes": 0,
        "seconds": 11,
        "percent": 0.01
      },
      {
        "name": "post-teams-$teamId-billing-sync",
        "total_seconds": 11.952183,
        "digital": "0:00:11",
        "decimal": "0.00",
        "text": "11 secs",
        "hours": 0,
        "minutes": 0,
        "seconds": 11,
        "percent": 0.01
      },
      {
        "name": "use-credits-consumed",
        "total_seconds": 11.755574,
        "digital": "0:00:11",
        "decimal": "0.00",
        "text": "11 secs",
        "hours": 0,
        "minutes": 0,
        "seconds": 11,
        "percent": 0.01
      },
      {
        "name": "use-team-slug",
        "total_seconds": 11.755574,
        "digital": "0:00:11",
        "decimal": "0.00",
        "text": "11 secs",
        "hours": 0,
        "minutes": 0,
        "seconds": 11,
        "percent": 0.01
      },
      {
        "name": "navbar-item-layout",
        "total_seconds": 8.647667,
        "digital": "0:00:08",
        "decimal": "0.00",
        "text": "8 secs",
        "hours": 0,
        "minutes": 0,
        "seconds": 8,
        "percent": 0.01
      },
      {
        "name": "dropdown-menu",
        "total_seconds": 8.647667,
        "digital": "0:00:08",
        "decimal": "0.00",
        "text": "8 secs",
        "hours": 0,
        "minutes": 0,
        "seconds": 8,
        "percent": 0.01
      },
      {
        "name": "nextjs",
        "total_seconds": 7.822581,
        "digital": "0:00:07",
        "decimal": "0.00",
        "text": "7 secs",
        "hours": 0,
        "minutes": 0,
        "seconds": 7,
        "percent": 0.01
      },
      {
        "name": "common",
        "total_seconds": 7.822581,
        "digital": "0:00:07",
        "decimal": "0.00",
        "text": "7 secs",
        "hours": 0,
        "minutes": 0,
        "seconds": 7,
        "percent": 0.01
      },
      {
        "name": "jwt-decode",
        "total_seconds": 7.822581,
        "digital": "0:00:07",
        "decimal": "0.00",
        "text": "7 secs",
        "hours": 0,
        "minutes": 0,
        "seconds": 7,
        "percent": 0.01
      },
      {
        "name": "http-status",
        "total_seconds": 7.822581,
        "digital": "0:00:07",
        "decimal": "0.00",
        "text": "7 secs",
        "hours": 0,
        "minutes": 0,
        "seconds": 7,
        "percent": 0.01
      },
      {
        "name": "frontend",
        "total_seconds": 7.822581,
        "digital": "0:00:07",
        "decimal": "0.00",
        "text": "7 secs",
        "hours": 0,
        "minutes": 0,
        "seconds": 7,
        "percent": 0.01
      },
      {
        "name": "textarea",
        "total_seconds": 7.373314,
        "digital": "0:00:07",
        "decimal": "0.00",
        "text": "7 secs",
        "hours": 0,
        "minutes": 0,
        "seconds": 7,
        "percent": 0
      },
      {
        "name": "view-close-button",
        "total_seconds": 6.578787,
        "digital": "0:00:06",
        "decimal": "0.00",
        "text": "6 secs",
        "hours": 0,
        "minutes": 0,
        "seconds": 6,
        "percent": 0
      },
      {
        "name": "view-body",
        "total_seconds": 6.578787,
        "digital": "0:00:06",
        "decimal": "0.00",
        "text": "6 secs",
        "hours": 0,
        "minutes": 0,
        "seconds": 6,
        "percent": 0
      },
      {
        "name": "use-has-left-sidebar",
        "total_seconds": 6.578787,
        "digital": "0:00:06",
        "decimal": "0.00",
        "text": "6 secs",
        "hours": 0,
        "minutes": 0,
        "seconds": 6,
        "percent": 0
      },
      {
        "name": "view-header",
        "total_seconds": 6.578787,
        "digital": "0:00:06",
        "decimal": "0.00",
        "text": "6 secs",
        "hours": 0,
        "minutes": 0,
        "seconds": 6,
        "percent": 0
      },
      {
        "name": "view-sidebar",
        "total_seconds": 6.578787,
        "digital": "0:00:06",
        "decimal": "0.00",
        "text": "6 secs",
        "hours": 0,
        "minutes": 0,
        "seconds": 6,
        "percent": 0
      },
      {
        "name": "view-main",
        "total_seconds": 6.578787,
        "digital": "0:00:06",
        "decimal": "0.00",
        "text": "6 secs",
        "hours": 0,
        "minutes": 0,
        "seconds": 6,
        "percent": 0
      },
      {
        "name": "view-root",
        "total_seconds": 6.578787,
        "digital": "0:00:06",
        "decimal": "0.00",
        "text": "6 secs",
        "hours": 0,
        "minutes": 0,
        "seconds": 6,
        "percent": 0
      },
      {
        "name": "popover",
        "total_seconds": 6.05109,
        "digital": "0:00:06",
        "decimal": "0.00",
        "text": "6 secs",
        "hours": 0,
        "minutes": 0,
        "seconds": 6,
        "percent": 0
      },
      {
        "name": "accordion",
        "total_seconds": 6.05109,
        "digital": "0:00:06",
        "decimal": "0.00",
        "text": "6 secs",
        "hours": 0,
        "minutes": 0,
        "seconds": 6,
        "percent": 0
      },
      {
        "name": "skeleton",
        "total_seconds": 6.05109,
        "digital": "0:00:06",
        "decimal": "0.00",
        "text": "6 secs",
        "hours": 0,
        "minutes": 0,
        "seconds": 6,
        "percent": 0
      },
      {
        "name": "radio-group",
        "total_seconds": 6.05109,
        "digital": "0:00:06",
        "decimal": "0.00",
        "text": "6 secs",
        "hours": 0,
        "minutes": 0,
        "seconds": 6,
        "percent": 0
      },
      {
        "name": "generations-modal",
        "total_seconds": 6.05109,
        "digital": "0:00:06",
        "decimal": "0.00",
        "text": "6 secs",
        "hours": 0,
        "minutes": 0,
        "seconds": 6,
        "percent": 0
      },
      {
        "name": "use-wait-until",
        "total_seconds": 6.05109,
        "digital": "0:00:06",
        "decimal": "0.00",
        "text": "6 secs",
        "hours": 0,
        "minutes": 0,
        "seconds": 6,
        "percent": 0
      },
      {
        "name": "timeago",
        "total_seconds": 5.613263,
        "digital": "0:00:05",
        "decimal": "0.00",
        "text": "5 secs",
        "hours": 0,
        "minutes": 0,
        "seconds": 5,
        "percent": 0
      },
      {
        "name": "avatar",
        "total_seconds": 5.474728,
        "digital": "0:00:05",
        "decimal": "0.00",
        "text": "5 secs",
        "hours": 0,
        "minutes": 0,
        "seconds": 5,
        "percent": 0
      },
      {
        "name": "page",
        "total_seconds": 2.596577,
        "digital": "0:00:02",
        "decimal": "0.00",
        "text": "2 secs",
        "hours": 0,
        "minutes": 0,
        "seconds": 2,
        "percent": 0
      },
      {
        "name": "data",
        "total_seconds": 2.596577,
        "digital": "0:00:02",
        "decimal": "0.00",
        "text": "2 secs",
        "hours": 0,
        "minutes": 0,
        "seconds": 2,
        "percent": 0
      },
      {
        "name": "image",
        "total_seconds": 2.458042,
        "digital": "0:00:02",
        "decimal": "0.00",
        "text": "2 secs",
        "hours": 0,
        "minutes": 0,
        "seconds": 2,
        "percent": 0
      },
      {
        "name": "view-link",
        "total_seconds": 2.458042,
        "digital": "0:00:02",
        "decimal": "0.00",
        "text": "2 secs",
        "hours": 0,
        "minutes": 0,
        "seconds": 2,
        "percent": 0
      },
      {
        "name": "switch",
        "total_seconds": 2.458042,
        "digital": "0:00:02",
        "decimal": "0.00",
        "text": "2 secs",
        "hours": 0,
        "minutes": 0,
        "seconds": 2,
        "percent": 0
      },
      {
        "name": "normalized-data-card",
        "total_seconds": 2.458042,
        "digital": "0:00:02",
        "decimal": "0.00",
        "text": "2 secs",
        "hours": 0,
        "minutes": 0,
        "seconds": 2,
        "percent": 0
      },
      {
        "name": "label",
        "total_seconds": 2.458042,
        "digital": "0:00:02",
        "decimal": "0.00",
        "text": "2 secs",
        "hours": 0,
        "minutes": 0,
        "seconds": 2,
        "percent": 0
      },
      {
        "name": "toggle-group",
        "total_seconds": 1.322224,
        "digital": "0:00:01",
        "decimal": "0.00",
        "text": "1 sec",
        "hours": 0,
        "minutes": 0,
        "seconds": 1,
        "percent": 0
      },
      {
        "name": "patch-teams-$teamId-billing",
        "total_seconds": 1.237717,
        "digital": "0:00:01",
        "decimal": "0.00",
        "text": "1 sec",
        "hours": 0,
        "minutes": 0,
        "seconds": 1,
        "percent": 0
      },
      {
        "name": "react-popover",
        "total_seconds": 0.930242,
        "digital": "0:00:00",
        "decimal": "0.00",
        "text": "0 secs",
        "hours": 0,
        "minutes": 0,
        "seconds": 0,
        "percent": 0
      }
    ],
    "machines": [
      {
        "name": "Anand's+MacBook+Pro",
        "total_seconds": 15230.275483,
        "machine_name_id": "018d2788-708d-4f43-a7cf-8c3020a4b466",
        "digital": "4:13:50",
        "decimal": "4.22",
        "text": "4 hrs 13 mins",
        "hours": 4,
        "minutes": 13,
        "seconds": 50,
        "percent": 98.47
      },
      {
        "name": "Anand%27s+MacBook+Pro",
        "total_seconds": 236.62674,
        "machine_name_id": "018e510a-e46b-4be4-b7c6-eca6133ad025",
        "digital": "0:03:56",
        "decimal": "0.05",
        "text": "3 mins",
        "hours": 0,
        "minutes": 3,
        "seconds": 56,
        "percent": 1.53
      }
    ],
    "projects": [
      {
        "name": "firstquadrant",
        "total_seconds": 15466.902223,
        "color": null,
        "digital": "4:17:46",
        "decimal": "4.28",
        "text": "4 hrs 17 mins",
        "hours": 4,
        "minutes": 17,
        "seconds": 46,
        "percent": 100
      }
    ],
    "range": {
      "start": "2024-08-28T22:00:00Z",
      "end": "2024-08-29T21:59:59Z",
      "date": "2024-08-29",
      "text": "Thu Aug 29th 2024",
      "timezone": "Europe/Amsterdam"
    }
  }
]