[
  {
    "Rank": 1,
    "Time Spent (seconds)": 8398,
    "Number of People": 1,
    "Category": "Software Development"
  },
  {
    "Rank": 2,
    "Time Spent (seconds)": 5840,
    "Number of People": 1,
    "Category": "Communication & Scheduling"
  },
  {
    "Rank": 3,
    "Time Spent (seconds)": 5441,
    "Number of People": 1,
    "Category": "Entertainment"
  },
  {
    "Rank": 4,
    "Time Spent (seconds)": 5139,
    "Number of People": 1,
    "Category": "Reference & Learning"
  },
  {
    "Rank": 5,
    "Time Spent (seconds)": 1511,
    "Number of People": 1,
    "Category": "Social Networking"
  },
  {
    "Rank": 6,
    "Time Spent (seconds)": 1436,
    "Number of People": 1,
    "Category": "Utilities"
  },
  {
    "Rank": 7,
    "Time Spent (seconds)": 1060,
    "Number of People": 1,
    "Category": "Business"
  },
  {
    "Rank": 8,
    "Time Spent (seconds)": 1034,
    "Number of People": 1,
    "Category": "Uncategorized"
  },
  {
    "Rank": 9,
    "Time Spent (seconds)": 247,
    "Number of People": 1,
    "Category": "News & Opinion"
  },
  {
    "Rank": 10,
    "Time Spent (seconds)": 35,
    "Number of People": 1,
    "Category": "Design & Composition"
  },
  {
    "Rank": 11,
    "Time Spent (seconds)": 12,
    "Number of People": 1,
    "Category": "Shopping"
  }
]