[
  {
    "artist": {
      "mbid": "c2f6c57f-27ba-4c0d-b2fd-3348961e79a1",
      "#text": "Maisie Peters"
    },
    "streamable": "0",
    "image": [
      {
        "size": "small",
        "#text": "https://lastfm.freetls.fastly.net/i/u/34s/860725da15e4dd42f642ed3328d669c7.jpg"
      },
      {
        "size": "medium",
        "#text": "https://lastfm.freetls.fastly.net/i/u/64s/860725da15e4dd42f642ed3328d669c7.jpg"
      },
      {
        "size": "large",
        "#text": "https://lastfm.freetls.fastly.net/i/u/174s/860725da15e4dd42f642ed3328d669c7.jpg"
      },
      {
        "size": "extralarge",
        "#text": "https://lastfm.freetls.fastly.net/i/u/300x300/860725da15e4dd42f642ed3328d669c7.jpg"
      }
    ],
    "mbid": "",
    "album": {
      "mbid": "",
      "#text": "Cate’s Brother"
    },
    "name": "Cate’s Brother",
    "url": "https://www.last.fm/music/Maisie+Peters/_/Cate%E2%80%99s+Brother",
    "date": {
      "uts": "1660938653",
      "#text": "19 Aug 2022, 19:50"
    }
  },
  {
    "artist": {
      "mbid": "c2f6c57f-27ba-4c0d-b2fd-3348961e79a1",
      "#text": "Maisie Peters"
    },
    "streamable": "0",
    "image": [
      {
        "size": "small",
        "#text": "https://lastfm.freetls.fastly.net/i/u/34s/d6375389c611a9b8b1723715f4e426d3.jpg"
      },
      {
        "size": "medium",
        "#text": "https://lastfm.freetls.fastly.net/i/u/64s/d6375389c611a9b8b1723715f4e426d3.jpg"
      },
      {
        "size": "large",
        "#text": "https://lastfm.freetls.fastly.net/i/u/174s/d6375389c611a9b8b1723715f4e426d3.jpg"
      },
      {
        "size": "extralarge",
        "#text": "https://lastfm.freetls.fastly.net/i/u/300x300/d6375389c611a9b8b1723715f4e426d3.jpg"
      }
    ],
    "mbid": "",
    "album": {
      "mbid": "",
      "#text": "Blonde"
    },
    "name": "Blonde",
    "url": "https://www.last.fm/music/Maisie+Peters/_/Blonde",
    "date": {
      "uts": "1660926954",
      "#text": "19 Aug 2022, 16:35"
    }
  },
  {
    "artist": {
      "mbid": "c2f6c57f-27ba-4c0d-b2fd-3348961e79a1",
      "#text": "Maisie Peters"
    },
    "streamable": "0",
    "image": [
      {
        "size": "small",
        "#text": "https://lastfm.freetls.fastly.net/i/u/34s/52177cef88f6817c78cb71bf813045de.jpg"
      },
      {
        "size": "medium",
        "#text": "https://lastfm.freetls.fastly.net/i/u/64s/52177cef88f6817c78cb71bf813045de.jpg"
      },
      {
        "size": "large",
        "#text": "https://lastfm.freetls.fastly.net/i/u/174s/52177cef88f6817c78cb71bf813045de.jpg"
      },
      {
        "size": "extralarge",
        "#text": "https://lastfm.freetls.fastly.net/i/u/300x300/52177cef88f6817c78cb71bf813045de.jpg"
      }
    ],
    "mbid": "",
    "album": {
      "mbid": "",
      "#text": "Good Enough"
    },
    "name": "Good Enough",
    "url": "https://www.last.fm/music/Maisie+Peters/_/Good+Enough",
    "date": {
      "uts": "1660926732",
      "#text": "19 Aug 2022, 16:32"
    }
  },
  {
    "artist": {
      "mbid": "c2f6c57f-27ba-4c0d-b2fd-3348961e79a1",
      "#text": "Maisie Peters"
    },
    "streamable": "0",
    "image": [
      {
        "size": "small",
        "#text": "https://lastfm.freetls.fastly.net/i/u/34s/52177cef88f6817c78cb71bf813045de.jpg"
      },
      {
        "size": "medium",
        "#text": "https://lastfm.freetls.fastly.net/i/u/64s/52177cef88f6817c78cb71bf813045de.jpg"
      },
      {
        "size": "large",
        "#text": "https://lastfm.freetls.fastly.net/i/u/174s/52177cef88f6817c78cb71bf813045de.jpg"
      },
      {
        "size": "extralarge",
        "#text": "https://lastfm.freetls.fastly.net/i/u/300x300/52177cef88f6817c78cb71bf813045de.jpg"
      }
    ],
    "mbid": "",
    "album": {
      "mbid": "",
      "#text": "Good Enough"
    },
    "name": "Good Enough",
    "url": "https://www.last.fm/music/Maisie+Peters/_/Good+Enough",
    "date": {
      "uts": "1660892048",
      "#text": "19 Aug 2022, 06:54"
    }
  },
  {
    "artist": {
      "mbid": "c2f6c57f-27ba-4c0d-b2fd-3348961e79a1",
      "#text": "Maisie Peters"
    },
    "streamable": "0",
    "image": [
      {
        "size": "small",
        "#text": "https://lastfm.freetls.fastly.net/i/u/34s/52177cef88f6817c78cb71bf813045de.jpg"
      },
      {
        "size": "medium",
        "#text": "https://lastfm.freetls.fastly.net/i/u/64s/52177cef88f6817c78cb71bf813045de.jpg"
      },
      {
        "size": "large",
        "#text": "https://lastfm.freetls.fastly.net/i/u/174s/52177cef88f6817c78cb71bf813045de.jpg"
      },
      {
        "size": "extralarge",
        "#text": "https://lastfm.freetls.fastly.net/i/u/300x300/52177cef88f6817c78cb71bf813045de.jpg"
      }
    ],
    "mbid": "",
    "album": {
      "mbid": "",
      "#text": "Good Enough"
    },
    "name": "Good Enough",
    "url": "https://www.last.fm/music/Maisie+Peters/_/Good+Enough",
    "date": {
      "uts": "1660890794",
      "#text": "19 Aug 2022, 06:33"
    }
  },
  {
    "artist": {
      "mbid": "c2f6c57f-27ba-4c0d-b2fd-3348961e79a1",
      "#text": "Maisie Peters"
    },
    "streamable": "0",
    "image": [
      {
        "size": "small",
        "#text": "https://lastfm.freetls.fastly.net/i/u/34s/28fc5c69cb659313fdbcb31aba853546.jpg"
      },
      {
        "size": "medium",
        "#text": "https://lastfm.freetls.fastly.net/i/u/64s/28fc5c69cb659313fdbcb31aba853546.jpg"
      },
      {
        "size": "large",
        "#text": "https://lastfm.freetls.fastly.net/i/u/174s/28fc5c69cb659313fdbcb31aba853546.jpg"
      },
      {
        "size": "extralarge",
        "#text": "https://lastfm.freetls.fastly.net/i/u/300x300/28fc5c69cb659313fdbcb31aba853546.jpg"
      }
    ],
    "mbid": "",
    "album": {
      "mbid": "",
      "#text": "Cate’s Brother (Matt's Version)"
    },
    "name": "Cate’s Brother - Matt's Version",
    "url": "https://www.last.fm/music/Maisie+Peters/_/Cate%E2%80%99s+Brother+-+Matt%27s+Version",
    "date": {
      "uts": "1660890596",
      "#text": "19 Aug 2022, 06:29"
    }
  },
  {
    "artist": {
      "mbid": "c2f6c57f-27ba-4c0d-b2fd-3348961e79a1",
      "#text": "Maisie Peters"
    },
    "streamable": "0",
    "image": [
      {
        "size": "small",
        "#text": "https://lastfm.freetls.fastly.net/i/u/34s/876f078f65a69f67823fd0336bbd3e68.jpg"
      },
      {
        "size": "medium",
        "#text": "https://lastfm.freetls.fastly.net/i/u/64s/876f078f65a69f67823fd0336bbd3e68.jpg"
      },
      {
        "size": "large",
        "#text": "https://lastfm.freetls.fastly.net/i/u/174s/876f078f65a69f67823fd0336bbd3e68.jpg"
      },
      {
        "size": "extralarge",
        "#text": "https://lastfm.freetls.fastly.net/i/u/300x300/876f078f65a69f67823fd0336bbd3e68.jpg"
      }
    ],
    "mbid": "",
    "album": {
      "mbid": "",
      "#text": "Cate’s Brother (BRELAND's Version)"
    },
    "name": "Cate’s Brother - BRELAND's Version",
    "url": "https://www.last.fm/music/Maisie+Peters/_/Cate%E2%80%99s+Brother+-+BRELAND%27s+Version",
    "date": {
      "uts": "1660890415",
      "#text": "19 Aug 2022, 06:26"
    }
  },
  {
    "artist": {
      "mbid": "c2f6c57f-27ba-4c0d-b2fd-3348961e79a1",
      "#text": "Maisie Peters"
    },
    "streamable": "0",
    "image": [
      {
        "size": "small",
        "#text": "https://lastfm.freetls.fastly.net/i/u/34s/860725da15e4dd42f642ed3328d669c7.jpg"
      },
      {
        "size": "medium",
        "#text": "https://lastfm.freetls.fastly.net/i/u/64s/860725da15e4dd42f642ed3328d669c7.jpg"
      },
      {
        "size": "large",
        "#text": "https://lastfm.freetls.fastly.net/i/u/174s/860725da15e4dd42f642ed3328d669c7.jpg"
      },
      {
        "size": "extralarge",
        "#text": "https://lastfm.freetls.fastly.net/i/u/300x300/860725da15e4dd42f642ed3328d669c7.jpg"
      }
    ],
    "mbid": "",
    "album": {
      "mbid": "",
      "#text": "Cate’s Brother"
    },
    "name": "Cate’s Brother",
    "url": "https://www.last.fm/music/Maisie+Peters/_/Cate%E2%80%99s+Brother",
    "date": {
      "uts": "1660890234",
      "#text": "19 Aug 2022, 06:23"
    }
  },
  {
    "artist": {
      "mbid": "c2f6c57f-27ba-4c0d-b2fd-3348961e79a1",
      "#text": "Maisie Peters"
    },
    "streamable": "0",
    "image": [
      {
        "size": "small",
        "#text": "https://lastfm.freetls.fastly.net/i/u/34s/d6375389c611a9b8b1723715f4e426d3.jpg"
      },
      {
        "size": "medium",
        "#text": "https://lastfm.freetls.fastly.net/i/u/64s/d6375389c611a9b8b1723715f4e426d3.jpg"
      },
      {
        "size": "large",
        "#text": "https://lastfm.freetls.fastly.net/i/u/174s/d6375389c611a9b8b1723715f4e426d3.jpg"
      },
      {
        "size": "extralarge",
        "#text": "https://lastfm.freetls.fastly.net/i/u/300x300/d6375389c611a9b8b1723715f4e426d3.jpg"
      }
    ],
    "mbid": "",
    "album": {
      "mbid": "",
      "#text": "Blonde"
    },
    "name": "Blonde",
    "url": "https://www.last.fm/music/Maisie+Peters/_/Blonde",
    "date": {
      "uts": "1660890052",
      "#text": "19 Aug 2022, 06:20"
    }
  }
]