[
  {
    "grand_total": {
      "hours": 0,
      "minutes": 22,
      "total_seconds": 1331.044,
      "digital": "0:22",
      "decimal": "0.37",
      "text": "22 mins",
      "ai_additions": 0,
      "ai_deletions": 0,
      "human_additions": 27,
      "human_deletions": 52
    },
    "range": {
      "start": "2026-03-21T23:00:00Z",
      "end": "2026-03-22T22:59:59Z",
      "date": "2026-03-22",
      "text": "Sun Mar 22nd 2026",
      "timezone": "Europe/Amsterdam"
    },
    "projects": [
      {
        "name": "website",
        "total_seconds": 1331.044,
        "ai_additions": 0,
        "ai_deletions": 0,
        "human_additions": 27,
        "human_deletions": 52,
        "color": null,
        "digital": "0:22:11",
        "decimal": "0.37",
        "text": "22 mins",
        "hours": 0,
        "minutes": 22,
        "seconds": 11,
        "percent": 100
      }
    ],
    "languages": [
      {
        "name": "Astro",
        "total_seconds": 898.297,
        "digital": "0:14:58",
        "decimal": "0.23",
        "text": "14 mins",
        "hours": 0,
        "minutes": 14,
        "seconds": 58,
        "percent": 67.49
      },
      {
        "name": "TypeScript",
        "total_seconds": 305.796,
        "digital": "0:05:05",
        "decimal": "0.08",
        "text": "5 mins",
        "hours": 0,
        "minutes": 5,
        "seconds": 5,
        "percent": 22.97
      },
      {
        "name": "CSS",
        "total_seconds": 44.473,
        "digital": "0:00:44",
        "decimal": "0.00",
        "text": "44 secs",
        "hours": 0,
        "minutes": 0,
        "seconds": 44,
        "percent": 3.34
      },
      {
        "name": "JSON",
        "total_seconds": 42.005,
        "digital": "0:00:42",
        "decimal": "0.00",
        "text": "42 secs",
        "hours": 0,
        "minutes": 0,
        "seconds": 42,
        "percent": 3.16
      },
      {
        "name": "JavaScript",
        "total_seconds": 22.768,
        "digital": "0:00:22",
        "decimal": "0.00",
        "text": "22 secs",
        "hours": 0,
        "minutes": 0,
        "seconds": 22,
        "percent": 1.71
      },
      {
        "name": "Markdown",
        "total_seconds": 17.705,
        "digital": "0:00:17",
        "decimal": "0.00",
        "text": "17 secs",
        "hours": 0,
        "minutes": 0,
        "seconds": 17,
        "percent": 1.33
      }
    ],
    "dependencies": [
      {
        "name": "Button",
        "total_seconds": 303.222,
        "digital": "0:05:03",
        "decimal": "0.08",
        "text": "5 mins",
        "hours": 0,
        "minutes": 5,
        "seconds": 3,
        "percent": 33.03
      },
      {
        "name": "react",
        "total_seconds": 303.222,
        "digital": "0:05:03",
        "decimal": "0.08",
        "text": "5 mins",
        "hours": 0,
        "minutes": 5,
        "seconds": 3,
        "percent": 33.03
      },
      {
        "name": "LogoMark",
        "total_seconds": 303.222,
        "digital": "0:05:03",
        "decimal": "0.08",
        "text": "5 mins",
        "hours": 0,
        "minutes": 5,
        "seconds": 3,
        "percent": 33.03
      },
      {
        "name": "loaders",
        "total_seconds": 2.574,
        "digital": "0:00:02",
        "decimal": "0.00",
        "text": "2 secs",
        "hours": 0,
        "minutes": 0,
        "seconds": 2,
        "percent": 0.28
      },
      {
        "name": "astro:content",
        "total_seconds": 1.466,
        "digital": "0:00:01",
        "decimal": "0.00",
        "text": "1 sec",
        "hours": 0,
        "minutes": 0,
        "seconds": 1,
        "percent": 0.16
      },
      {
        "name": "content.config",
        "total_seconds": 1.108,
        "digital": "0:00:01",
        "decimal": "0.00",
        "text": "1 sec",
        "hours": 0,
        "minutes": 0,
        "seconds": 1,
        "percent": 0.12
      },
      {
        "name": "zod",
        "total_seconds": 1.108,
        "digital": "0:00:01",
        "decimal": "0.00",
        "text": "1 sec",
        "hours": 0,
        "minutes": 0,
        "seconds": 1,
        "percent": 0.12
      },
      {
        "name": "index",
        "total_seconds": 1.108,
        "digital": "0:00:01",
        "decimal": "0.00",
        "text": "1 sec",
        "hours": 0,
        "minutes": 0,
        "seconds": 1,
        "percent": 0.12
      },
      {
        "name": "astro",
        "total_seconds": 1.108,
        "digital": "0:00:01",
        "decimal": "0.00",
        "text": "1 sec",
        "hours": 0,
        "minutes": 0,
        "seconds": 1,
        "percent": 0.12
      }
    ],
    "machines": [
      {
        "name": "Mac.localdomain",
        "total_seconds": 1331.044,
        "machine_name_id": "32aa50fd-92f6-4c8f-ad2d-66db96195f92",
        "digital": "0:22:11",
        "decimal": "0.37",
        "text": "22 mins",
        "hours": 0,
        "minutes": 22,
        "seconds": 11,
        "percent": 100
      }
    ],
    "editors": [
      {
        "name": "Cursor",
        "total_seconds": 1331.044,
        "digital": "0:22:11",
        "decimal": "0.37",
        "text": "22 mins",
        "hours": 0,
        "minutes": 22,
        "seconds": 11,
        "percent": 100
      }
    ],
    "operating_systems": [
      {
        "name": "Mac",
        "total_seconds": 1331.044,
        "digital": "0:22:11",
        "decimal": "0.37",
        "text": "22 mins",
        "hours": 0,
        "minutes": 22,
        "seconds": 11,
        "percent": 100
      }
    ],
    "categories": [
      {
        "name": "Building",
        "total_seconds": 1275.827,
        "digital": "0:21:15",
        "decimal": "0.35",
        "text": "21 mins",
        "hours": 0,
        "minutes": 21,
        "seconds": 15,
        "percent": 95.85
      },
      {
        "name": "Coding",
        "total_seconds": 55.217,
        "digital": "0:00:55",
        "decimal": "0.00",
        "text": "55 secs",
        "hours": 0,
        "minutes": 0,
        "seconds": 55,
        "percent": 4.15
      }
    ]
  }
]