[
  {
    "id": "healthkit-208778B2-4B39-4FB5-9325-2EE8D26EB42C",
    "name": "Walking",
    "startTimeMillis": "1586012945916",
    "endTimeMillis": "1586013088789",
    "modifiedTimeMillis": "1597253360025",
    "application": {
      "packageName": "co.humanco.human",
      "version": "",
      "detailsUrl": "",
      "name": ""
    },
    "activityType": 93,
    "activeTimeMillis": "142000",
    "startTime": "2020-04-04T15:09:05.916Z",
    "endTime": "2020-04-04T15:11:28.789Z"
  },
  {
    "id": "healthkit-24260F59-ABA7-4B2E-A7FD-BD6FB1E5240C",
    "name": "Walking",
    "startTimeMillis": "1586017365874",
    "endTimeMillis": "1586017464680",
    "modifiedTimeMillis": "1597253355689",
    "application": {
      "packageName": "co.humanco.human",
      "version": "",
      "detailsUrl": "",
      "name": ""
    },
    "activityType": 93,
    "activeTimeMillis": "98000",
    "startTime": "2020-04-04T16:22:45.874Z",
    "endTime": "2020-04-04T16:24:24.680Z"
  },
  {
    "id": "healthkit-351263D6-873B-4456-992B-BCB08E4C88D3",
    "name": "Walking",
    "startTimeMillis": "1586018761228",
    "endTimeMillis": "1586018848612",
    "modifiedTimeMillis": "1597253358937",
    "application": {
      "packageName": "co.humanco.human",
      "version": "",
      "detailsUrl": "",
      "name": ""
    },
    "activityType": 93,
    "activeTimeMillis": "87000",
    "startTime": "2020-04-04T16:46:01.228Z",
    "endTime": "2020-04-04T16:47:28.612Z"
  },
  {
    "id": "healthkit-414753DD-D479-4982-8255-F210B4D39D49",
    "name": "Walking",
    "startTimeMillis": "1586014614923",
    "endTimeMillis": "1586014763046",
    "modifiedTimeMillis": "1597253362255",
    "application": {
      "packageName": "co.humanco.human",
      "version": "",
      "detailsUrl": "",
      "name": ""
    },
    "activityType": 93,
    "activeTimeMillis": "148000",
    "startTime": "2020-04-04T15:36:54.923Z",
    "endTime": "2020-04-04T15:39:23.046Z"
  },
  {
    "id": "healthkit-4A92DF74-228D-4B15-BD2E-194DEDA6DD3F",
    "name": "Walking",
    "startTimeMillis": "1586014979966",
    "endTimeMillis": "1586015125378",
    "modifiedTimeMillis": "1597253356805",
    "application": {
      "packageName": "co.humanco.human",
      "version": "",
      "detailsUrl": "",
      "name": ""
    },
    "activityType": 93,
    "activeTimeMillis": "145000",
    "startTime": "2020-04-04T15:42:59.966Z",
    "endTime": "2020-04-04T15:45:25.378Z"
  },
  {
    "id": "healthkit-87FDEAD8-EC8C-4DC9-A099-377E1B70FF17",
    "name": "Walking",
    "startTimeMillis": "1585996650302",
    "endTimeMillis": "1585996723656",
    "modifiedTimeMillis": "1597253356440",
    "application": {
      "packageName": "co.humanco.human",
      "version": "",
      "detailsUrl": "",
      "name": ""
    },
    "activityType": 93,
    "activeTimeMillis": "73000",
    "startTime": "2020-04-04T10:37:30.302Z",
    "endTime": "2020-04-04T10:38:43.656Z"
  },
  {
    "id": "healthkit-A29AD7CA-A117-408A-BC5F-6D0647D4165D",
    "name": "Walking",
    "startTimeMillis": "1586000106004",
    "endTimeMillis": "1586000184788",
    "modifiedTimeMillis": "1597253356383",
    "application": {
      "packageName": "co.humanco.human",
      "version": "",
      "detailsUrl": "",
      "name": ""
    },
    "activityType": 93,
    "activeTimeMillis": "78000",
    "startTime": "2020-04-04T11:35:06.004Z",
    "endTime": "2020-04-04T11:36:24.788Z"
  },
  {
    "id": "healthkit-BF2713F2-5983-435E-A657-EB074129CB3C",
    "name": "Walking",
    "startTimeMillis": "1585998510618",
    "endTimeMillis": "1585999105448",
    "modifiedTimeMillis": "1597253358115",
    "application": {
      "packageName": "co.humanco.human",
      "version": "",
      "detailsUrl": "",
      "name": ""
    },
    "activityType": 93,
    "activeTimeMillis": "594000",
    "startTime": "2020-04-04T11:08:30.618Z",
    "endTime": "2020-04-04T11:18:25.448Z"
  }
]